dudocode/__init__.py
dudocode/dudo.py
dudocode/version.py
dudocode/objects/__init__.py
dudocode/objects/classes.py
dudocode/objects/functions.py
dudocode/objects/macros.py
dudocode/transpile/__init__.py
dudocode/transpile/transpiler.py
dudocode/transpiler/__init__.py
dudocode/transpiler/functools.py
dudocode/transpiler/transpiler.py
dudocode/utils/__init__.py
dudocode/utils/utils.py
dudocode-0.6.1.dist-info/LICENSE
dudocode-0.6.1.dist-info/METADATA
dudocode-0.6.1.dist-info/WHEEL
dudocode-0.6.1.dist-info/entry_points.txt
dudocode-0.6.1.dist-info/top_level.txt
dudocode-0.6.1.dist-info/RECORD
