Metadata-Version: 2.1
Name: dudocode
Version: 0.6.1
Summary: A pseudocode-to-Python transpiler based on the format specified in CIE IGCSE (Syllabus 0478)
Home-page: https://github.com/PerceptronV/dudocode
Author: PerceptronV
Author-email: neutrinovs@gmail.com
License: UNKNOWN
Platform: UNKNOWN
Classifier: Programming Language :: Other
Classifier: Intended Audience :: Developers
Classifier: Intended Audience :: Education
Classifier: License :: Free for non-commercial use
Classifier: Operating System :: OS Independent
Classifier: Topic :: Software Development :: Interpreters
Classifier: Development Status :: 4 - Beta
Classifier: Environment :: Console
Classifier: Natural Language :: English
Requires-Python: >=3.3
License-File: LICENSE
Requires-Dist: numpy
Requires-Dist: trilobyte
Requires-Dist: colorama
